{
  "/_not-found/page": "app/_not-found/page.js",
  "/api/auth/login/route": "app/api/auth/login/route.js",
  "/api/auth/change-password/route": "app/api/auth/change-password/route.js",
  "/api/cash-register/history/route": "app/api/cash-register/history/route.js",
  "/api/customers/route": "app/api/customers/route.js",
  "/api/finance/treasury/route": "app/api/finance/treasury/route.js",
  "/api/finance/receivables/route": "app/api/finance/receivables/route.js",
  "/api/orders/[id]/route": "app/api/orders/[id]/route.js",
  "/api/products/[id]/route": "app/api/products/[id]/route.js",
  "/api/cash-register/route": "app/api/cash-register/route.js",
  "/api/users/[id]/route": "app/api/users/[id]/route.js",
  "/api/orders/route": "app/api/orders/route.js",
  "/api/stock/restock/route": "app/api/stock/restock/route.js",
  "/api/upload/route": "app/api/upload/route.js",
  "/api/users/route": "app/api/users/route.js",
  "/change-password/page": "app/change-password/page.js",
  "/login/page": "app/login/page.js",
  "/products/[id]/page": "app/products/[id]/page.js",
  "/page": "app/page.js",
  "/api/debug-connection/route": "app/api/debug-connection/route.js",
  "/api/products/route": "app/api/products/route.js",
  "/api/settings/route": "app/api/settings/route.js",
  "/(admin)/orders/[id]/page": "app/(admin)/orders/[id]/page.js",
  "/(admin)/products/new/page": "app/(admin)/products/new/page.js",
  "/(admin)/orders/page": "app/(admin)/orders/page.js",
  "/(admin)/clientes/page": "app/(admin)/clientes/page.js",
  "/(admin)/pos/page": "app/(admin)/pos/page.js",
  "/(admin)/settings/page": "app/(admin)/settings/page.js",
  "/(admin)/products/[id]/edit/page": "app/(admin)/products/[id]/edit/page.js",
  "/(admin)/dashboard/page": "app/(admin)/dashboard/page.js",
  "/(admin)/products/page": "app/(admin)/products/page.js",
  "/(admin)/caixas/page": "app/(admin)/caixas/page.js",
  "/(admin)/finance/page": "app/(admin)/finance/page.js",
  "/(admin)/financeiro/page": "app/(admin)/financeiro/page.js"
}